<zrx:explain xmlns:c3="http://www.cheshire3.org/schemas/explain/" xmlns:zrx="http://explain.z3950.org/dtd/2.0/" authoritative="true" id="db_clic">
  <zrx:serverInfo version="1.1" protocol="srw/u" transport="http">
    <zrx:host>COLCAL-1AJFVH8.local</zrx:host>
    <zrx:port>80</zrx:port>
    <zrx:database>api/sru/db_clic</zrx:database>
  </zrx:serverInfo>
  <zrx:databaseInfo>
    <zrx:title></zrx:title>
    <zrx:description></zrx:description>
  </zrx:databaseInfo>
  <zrx:metaInfo>
    <zrx:dateModified>2015-09-17T15:43:04.830369</zrx:dateModified>
  </zrx:metaInfo>
  <zrx:schemaInfo/>
  <zrx:indexInfo>
    <zrx:set identifier="info:srw/cql-context-set/1/cql-v1.2" name="cql"/>
    <zrx:set identifier="info:srw/cql-context-set/1/dc-v1.1" name="dc"/>
    <zrx:set identifier="info:srw/cql-context-set/2/rec-1.1" name="rec"/>
    <zrx:index c3:index="idx-identifier">
      <zrx:title>Record Identifier</zrx:title>
      <zrx:map>
        <zrx:name set="rec">identifier</zrx:name>
      </zrx:map>
      <zrx:configInfo>
        <zrx:supports type="relation">exact</zrx:supports>
        <zrx:supports type="relation">=</zrx:supports>
        <zrx:supports type="relation">any</zrx:supports>
        <zrx:supports type="relation">all</zrx:supports>
        <zrx:supports type="relation">&lt;</zrx:supports>
        <zrx:supports type="relation">&lt;=</zrx:supports>
        <zrx:supports type="relation">&gt;</zrx:supports>
        <zrx:supports type="relation">&gt;=</zrx:supports>
        <zrx:supports type="relation">within</zrx:supports>
      </zrx:configInfo>
    </zrx:index>
    <zrx:index c3:index="idx-creationDate">
      <zrx:title>Record Creation Date</zrx:title>
      <zrx:map>
        <zrx:name set="rec">creationDate</zrx:name>
      </zrx:map>
      <zrx:configInfo>
        <zrx:supports type="relation">exact</zrx:supports>
        <zrx:supports type="relation">=</zrx:supports>
        <zrx:supports type="relation">&lt;</zrx:supports>
        <zrx:supports type="relation">&lt;=</zrx:supports>
        <zrx:supports type="relation">&gt;</zrx:supports>
        <zrx:supports type="relation">&gt;=</zrx:supports>
        <zrx:supports type="relation">within</zrx:supports>
      </zrx:configInfo>
    </zrx:index>
    <zrx:index c3:index="idx-modificationDate">
      <zrx:title>Record Modification Date</zrx:title>
      <zrx:map>
        <zrx:name set="rec">modificationDate</zrx:name>
      </zrx:map>
      <zrx:configInfo>
        <zrx:supports type="relation">exact</zrx:supports>
        <zrx:supports type="relation">=</zrx:supports>
        <zrx:supports type="relation">&lt;</zrx:supports>
        <zrx:supports type="relation">&lt;=</zrx:supports>
        <zrx:supports type="relation">&gt;</zrx:supports>
        <zrx:supports type="relation">&gt;=</zrx:supports>
        <zrx:supports type="relation">within</zrx:supports>
      </zrx:configInfo>
    </zrx:index>
    <zrx:index c3:index="idx-anywhere">
      <zrx:title>Anywhere / Full-text Keywords</zrx:title>
      <zrx:map>
        <zrx:name set="cql">anywhere</zrx:name>
      </zrx:map>
      <zrx:configInfo>
        <zrx:supports type="relation">=</zrx:supports>
        <zrx:supports type="relation">any</zrx:supports>
        <zrx:supports type="relation">all</zrx:supports>
        <zrx:supports type="relationModifier">word</zrx:supports>
      </zrx:configInfo>
    </zrx:index>
    <zrx:index c3:index="idx-title">
      <zrx:title>Title</zrx:title>
      <zrx:map>
        <zrx:name set="dc">title</zrx:name>
      </zrx:map>
      <zrx:configInfo>
        <zrx:supports type="relation">exact</zrx:supports>
        <zrx:supports type="relation">=</zrx:supports>
        <zrx:supports type="relation" c3:index="idx-title-kwd">any</zrx:supports>
        <zrx:supports type="relation" c3:index="idx-title-kwd">all</zrx:supports>
        <zrx:supports type="relationModifier">string</zrx:supports>
        <zrx:supports type="relationModifier" c3:index="idx-title-kwd">word</zrx:supports>
        <zrx:supports type="relationModifier" c3:index="idx-title-kwd">stem</zrx:supports>
      </zrx:configInfo>
    </zrx:index>
  </zrx:indexInfo>
  <zrx:configInfo>
    <zrx:default type="numberOfRecords">1</zrx:default>
    <zrx:default type="contextSet">cql</zrx:default>
    <zrx:default type="index">cql.anywhere</zrx:default>
    <zrx:default type="relation">all</zrx:default>
    <zrx:default type="sortCaseSensitive">false</zrx:default>
    <zrx:default type="sortAscending">true</zrx:default>
    <zrx:default type="sortMissingValue">HighValue</zrx:default>
    <zrx:setting type="maximumRecords">50</zrx:setting>
    <zrx:supports type="resultSets"/>
    <zrx:supports type="sort"/>
    <zrx:supports type="relationModifier">relevant</zrx:supports>
    <zrx:supports type="relationModifier">word</zrx:supports>
  </zrx:configInfo>
</zrx:explain>
